rotab/.python-version
rotab/__init__.py
rotab/ast/__init__.py
rotab/ast/context/params.py
rotab/ast/context/schema.py
rotab/ast/context/validation_context.py
rotab/ast/io_node.py
rotab/ast/node.py
rotab/ast/process_node.py
rotab/ast/step_node.py
rotab/ast/template_node.py
rotab/ast/util.py
rotab/cli/cli.py
rotab/core/__init__.py
rotab/core/operation/__init__.py
rotab/core/operation/derive_funcs_pandas.py
rotab/core/operation/derive_funcs_polars.py
rotab/core/operation/transform_funcs_pandas.py
rotab/core/operation/transform_funcs_polars.py
rotab/core/parse/parse.py
rotab/core/parse/parse_statement.py
rotab/core/pipeline.py
rotab/init/__init__.py
rotab/init/initialize.py
rotab/loader/__init__.py
rotab/loader/context_builder.py
rotab/loader/loader.py
rotab/loader/macro_expander.py
rotab/loader/parameter_resolver.py
rotab/loader/schema_manager.py
"rotab/runtime/__init__,py"
rotab/runtime/code_generator.py
rotab/runtime/dag_generator.py
rotab/runtime/sitecustomize.py
rotab/utils/__init__.py
rotab/utils/logger.py
rotab-0.3.15.dist-info/LICENCE
rotab-0.3.15.dist-info/METADATA
rotab-0.3.15.dist-info/WHEEL
rotab-0.3.15.dist-info/entry_points.txt
rotab-0.3.15.dist-info/RECORD
