Metadata-Version: 2.1
Name: rotab
Version: 0.3.15
Summary: ROTAB: a template that moves with your thinking.
Home-page: https://github.com/project-ro/rotab
License: MIT
Author: yuta.itatsu
Author-email: yuta.itatsu@gmail.com
Requires-Python: >=3.9,<4.0
Classifier: Development Status :: 2 - Pre-Alpha
Classifier: Intended Audience :: Developers
Classifier: License :: OSI Approved :: MIT License
Classifier: Programming Language :: Python :: 3
Classifier: Programming Language :: Python :: 3.9
Classifier: Programming Language :: Python :: 3.10
Classifier: Programming Language :: Python :: 3.11
Classifier: Programming Language :: Python :: 3.12
Requires-Dist: fsspec (>=2023.0.0,<2026.0.0)
Requires-Dist: joblib (>=1.5.1,<2.0.0)
Requires-Dist: kaleido (>=0.2.1,<1.1.0)
Requires-Dist: lightgbm (>=4.6.0,<5.0.0)
Requires-Dist: optuna (>=4.4.0,<5.0.0)
Requires-Dist: optuna-integration[lightgbm] (>=4.4.0,<5.0.0)
Requires-Dist: pandas (>=1.5.0,<3.0.0)
Requires-Dist: plotly (>=5.3.1,<6.3.0)
Requires-Dist: polars (>=1.31.0,<2.0.0)
Requires-Dist: pydantic (>=2.10.0,<3.0.0)
Requires-Dist: pyyaml (>=6.0.0,<7.0.0)
Requires-Dist: questionary (>=2.1.0,<3.0.0)
Requires-Dist: ruamel-yaml (>=0.18.14,<0.19.0)
Requires-Dist: s3fs (>=2023.0.0,<2026.0.0)
Requires-Dist: shap (>=0.48.0,<0.49.0)
Requires-Dist: typer (>=0.4.0,<1.0.0)
Requires-Dist: typing_extensions (>=4.0,<5.0)
Project-URL: Repository, https://github.com/project-ro/rotab
